converter21/ABCConverter.py
converter21/HumdrumConverter.py
converter21/MEIConverter.py
converter21/__init__.py
converter21/__main__.py
converter21/py.typed
converter21/abc/__init__.py
converter21/abc/abc2xml.py
converter21/abc/abcmetadata.py
converter21/abc/abcreader.py
converter21/abc/abcwriter.py
converter21/abc/pyparsing.py
converter21/abc/xml2abc.py
converter21/humdrum/__init__.py
converter21/humdrum/convert.py
converter21/humdrum/eventdata.py
converter21/humdrum/gridcommon.py
converter21/humdrum/gridmeasure.py
converter21/humdrum/gridpart.py
converter21/humdrum/gridside.py
converter21/humdrum/gridslice.py
converter21/humdrum/gridstaff.py
converter21/humdrum/gridvoice.py
converter21/humdrum/humaddress.py
converter21/humdrum/humdrumfile.py
converter21/humdrum/humdrumfilebase.py
converter21/humdrum/humdrumfilecontent.py
converter21/humdrum/humdrumfileset.py
converter21/humdrum/humdrumfilestream.py
converter21/humdrum/humdrumfilestructure.py
converter21/humdrum/humdrumline.py
converter21/humdrum/humdrumtoken.py
converter21/humdrum/humdrumtools.py
converter21/humdrum/humdrumwriter.py
converter21/humdrum/humexceptions.py
converter21/humdrum/humgrid.py
converter21/humdrum/humhash.py
converter21/humdrum/humnum.py
converter21/humdrum/humparamset.py
converter21/humdrum/humsignifiers.py
converter21/humdrum/m21convert.py
converter21/humdrum/measuredata.py
converter21/humdrum/partdata.py
converter21/humdrum/scoredata.py
converter21/humdrum/staffdata.py
converter21/mei/__init__.py
converter21/mei/m21objectconvert.py
converter21/mei/meielement.py
converter21/mei/meiexceptions.py
converter21/mei/meilayer.py
converter21/mei/meimeasure.py
converter21/mei/meimetadata.py
converter21/mei/meimetadatareader.py
converter21/mei/meireader.py
converter21/mei/meiscore.py
converter21/mei/meishared.py
converter21/mei/meistaff.py
converter21/mei/meiwriter.py
converter21/mei/test_meireader.py
converter21/shared/__init__.py
converter21/shared/debugutilities.py
converter21-4.0.0.dist-info/licenses/LICENSE
converter21-4.0.0.dist-info/METADATA
converter21-4.0.0.dist-info/WHEEL
converter21-4.0.0.dist-info/top_level.txt
converter21-4.0.0.dist-info/RECORD
