Metadata-Version: 2.4
Name: converter21
Version: 4.0.0
Summary: A music21-extending format converter package and command line tool (replaces music21's Humdrum and MEI parser, and adds a Humdrum writer and MEI writer)
Home-page: https://github.com/gregchapman-dev/converter21
Author: Greg Chapman
Author-email: gregc@mac.com
Project-URL: Source, https://github.com/gregchapman-dev/converter21
Project-URL: Bug Reports, https://github.com/gregchapman-dev/converter21/issues
Keywords: music,score,notation,converter,conversion,format,formats,humdrum,kern,krn,MEI,writer,parser,reader,music21,OMR,Optical Music Recognition,OMR-NED
Classifier: Development Status :: 5 - Production/Stable
Classifier: License :: OSI Approved :: MIT License
Classifier: Programming Language :: Python :: 3 :: Only
Classifier: Operating System :: OS Independent
Classifier: Natural Language :: English
Requires-Python: >=3.10
License-File: LICENSE
Requires-Dist: music21>=9.9.1
Dynamic: author
Dynamic: author-email
Dynamic: classifier
Dynamic: description
Dynamic: description-content-type
Dynamic: home-page
Dynamic: keywords
Dynamic: license-file
Dynamic: project-url
Dynamic: requires-dist
Dynamic: requires-python
Dynamic: summary
